advanced_alchemy/__init__.py
advanced_alchemy/__main__.py
advanced_alchemy/__metadata__.py
advanced_alchemy/_listeners.py
advanced_alchemy/_serialization.py
advanced_alchemy/base.py
advanced_alchemy/cli.py
advanced_alchemy/exceptions.py
advanced_alchemy/filters.py
advanced_alchemy/operations.py
advanced_alchemy/py.typed
advanced_alchemy/alembic/__init__.py
advanced_alchemy/alembic/commands.py
advanced_alchemy/alembic/utils.py
advanced_alchemy/alembic/templates/asyncio/README
advanced_alchemy/alembic/templates/asyncio/alembic.ini.mako
advanced_alchemy/alembic/templates/asyncio/env.py
advanced_alchemy/alembic/templates/asyncio/script.py.mako
advanced_alchemy/alembic/templates/sync/README
advanced_alchemy/alembic/templates/sync/alembic.ini.mako
advanced_alchemy/alembic/templates/sync/env.py
advanced_alchemy/alembic/templates/sync/script.py.mako
advanced_alchemy/config/__init__.py
advanced_alchemy/config/asyncio.py
advanced_alchemy/config/common.py
advanced_alchemy/config/engine.py
advanced_alchemy/config/sync.py
advanced_alchemy/config/types.py
advanced_alchemy/extensions/__init__.py
advanced_alchemy/extensions/fastapi/__init__.py
advanced_alchemy/extensions/fastapi/cli.py
advanced_alchemy/extensions/fastapi/config.py
advanced_alchemy/extensions/fastapi/extension.py
advanced_alchemy/extensions/fastapi/providers.py
advanced_alchemy/extensions/flask/__init__.py
advanced_alchemy/extensions/flask/cli.py
advanced_alchemy/extensions/flask/config.py
advanced_alchemy/extensions/flask/extension.py
advanced_alchemy/extensions/flask/utils.py
advanced_alchemy/extensions/litestar/__init__.py
advanced_alchemy/extensions/litestar/_utils.py
advanced_alchemy/extensions/litestar/cli.py
advanced_alchemy/extensions/litestar/dto.py
advanced_alchemy/extensions/litestar/exception_handler.py
advanced_alchemy/extensions/litestar/providers.py
advanced_alchemy/extensions/litestar/session.py
advanced_alchemy/extensions/litestar/store.py
advanced_alchemy/extensions/litestar/plugins/__init__.py
advanced_alchemy-1.8.2.dist-info/METADATA
advanced_alchemy-1.8.2.dist-info/WHEEL
advanced_alchemy-1.8.2.dist-info/entry_points.txt
advanced_alchemy-1.8.2.dist-info/licenses/LICENSE
advanced_alchemy-1.8.2.dist-info/RECORD
