Metadata-Version: 2.4
Name: advanced_alchemy
Version: 1.8.2
Summary: Ready-to-go SQLAlchemy concoctions.
Project-URL: Changelog, https://advanced-alchemy.dev/latest/changelog
Project-URL: Discord, https://discord.gg/litestar
Project-URL: Documentation, https://advanced-alchemy.dev/latest/
Project-URL: Funding, https://github.com/sponsors/litestar-org
Project-URL: Homepage, https://advanced-alchemy.dev/latest/
Project-URL: Issue, https://github.com/litestar-org/advanced-alchemy/issues/
Project-URL: Source, https://github.com/litestar-org/advanced-alchemy
Author-email: Cody Fincher <cody.fincher@gmail.com>, Peter Schutt <peter.github@proton.me>, Janek Nouvertné <j.a.nouvertne@posteo.de>, Jacob Coffee <jacob@z7x.org>
Maintainer-email: Litestar Developers <hello@litestar.dev>, Cody Fincher <cody@litestar.dev>, Jacob Coffee <jacob@litestar.dev>, Janek Nouvertné <janek@litestar.dev>, Julien Courtes <julien@litestar.dev>
License: MIT
License-File: LICENSE
Keywords: alembic,fastapi,flask,litestar,sanic,sqlalchemy
Classifier: Development Status :: 3 - Alpha
Classifier: Environment :: Web Environment
Classifier: Intended Audience :: Developers
Classifier: Intended Audience :: System Administrators
Classifier: License :: OSI Approved :: MIT License
Classifier: Natural Language :: English
Classifier: Operating System :: OS Independent
Classifier: Programming Language :: Python
Classifier: Programming Language :: Python :: 3.9
Classifier: Programming Language :: Python :: 3.10
Classifier: Programming Language :: Python :: 3.11
Classifier: Programming Language :: Python :: 3.12
Classifier: Programming Language :: Python :: 3.13
Classifier: Topic :: Database
Classifier: Topic :: Database :: Database Engines/Servers
Classifier: Topic :: Software Development
Classifier: Typing :: Typed
Requires-Python: >=3.9
Requires-Dist: alembic>=1.12.0
Requires-Dist: eval-type-backport; python_full_version < '3.10'
Requires-Dist: exceptiongroup; python_full_version < '3.11'
Requires-Dist: greenlet
Requires-Dist: sqlalchemy>=2.0.20
Requires-Dist: typing-extensions>=4.0.0
Provides-Extra: argon2
Requires-Dist: argon2-cffi; extra == 'argon2'
Provides-Extra: cli
Requires-Dist: rich-click; extra == 'cli'
Provides-Extra: fsspec
Requires-Dist: fsspec; extra == 'fsspec'
Provides-Extra: nanoid
Requires-Dist: fastnanoid>=0.4.1; extra == 'nanoid'
Provides-Extra: obstore
Requires-Dist: obstore; extra == 'obstore'
Provides-Extra: passlib
Requires-Dist: passlib[argon2]; extra == 'passlib'
Provides-Extra: pwdlib
Requires-Dist: pwdlib[argon2]; extra == 'pwdlib'
Provides-Extra: uuid
Requires-Dist: uuid-utils>=0.6.1; extra == 'uuid'
